NodeNotePackage/__init__.py
NodeNotePackage/Examples/__init__.py
NodeNotePackage/Examples/example.py
NodeNotePackage/NodeNote/__init__.py
NodeNotePackage/NodeNote/Components/__init__.py
NodeNotePackage/NodeNote/Components/attribute.py
NodeNotePackage/NodeNote/Components/draw.py
NodeNotePackage/NodeNote/Components/effect_background.py
NodeNotePackage/NodeNote/Components/effect_cutline.py
NodeNotePackage/NodeNote/Components/effect_snow.py
NodeNotePackage/NodeNote/Components/effect_water.py
NodeNotePackage/NodeNote/Components/pipe.py
NodeNotePackage/NodeNote/Components/port.py
NodeNotePackage/NodeNote/Components/sub_view.py
NodeNotePackage/NodeNote/Components/todo.py
NodeNotePackage/NodeNote/Components/window.py
NodeNotePackage/NodeNote/GraphicsView/__init__.py
NodeNotePackage/NodeNote/GraphicsView/app.py
NodeNotePackage/NodeNote/GraphicsView/scene.py
NodeNotePackage/NodeNote/GraphicsView/view.py
NodeNotePackage/NodeNote/Model/__init__.py
NodeNotePackage/NodeNote/Model/constants.py
NodeNotePackage/NodeNote/Model/history.py
NodeNotePackage/NodeNote/Model/serializable.py
NodeNotePackage/NodeNote/Model/serialize_pb2.py
NodeNotePackage/NodeNote/Model/stylesheet.py
NodeNotePackage/NodeNote/Resources/Attribute Widget.png
NodeNotePackage/NodeNote/Resources/Change Background Image.png
NodeNotePackage/NodeNote/Resources/Change flowing.png
NodeNotePackage/NodeNote/Resources/Colorful-Stingrays.svg
NodeNotePackage/NodeNote/Resources/Confetti-Doodles.svg
NodeNotePackage/NodeNote/Resources/Dalmatian-Spots.svg
NodeNotePackage/NodeNote/Resources/False.png
NodeNotePackage/NodeNote/Resources/Flat-Mountains.svg
NodeNotePackage/NodeNote/Resources/Flowers.png
NodeNotePackage/NodeNote/Resources/Pistachio.png
NodeNotePackage/NodeNote/Resources/Plane.png
NodeNotePackage/NodeNote/Resources/Radiant-Gradient.svg
NodeNotePackage/NodeNote/Resources/Todo.png
NodeNotePackage/NodeNote/Resources/True.png
NodeNotePackage/NodeNote/Resources/Truth Widget.png
NodeNotePackage-2.0.10.dist-info/LICENSE
NodeNotePackage-2.0.10.dist-info/METADATA
NodeNotePackage-2.0.10.dist-info/WHEEL
NodeNotePackage-2.0.10.dist-info/top_level.txt
NodeNotePackage-2.0.10.dist-info/RECORD
