Metadata-Version: 2.1
Name: NodeNotePackage
Version: 2.0.10
Summary: Mind map software
Home-page: https://github.com/yetao0806/NodeNote
Author: Ye Tao
Author-email: helper033@163.com
License: MPL
Platform: UNKNOWN
Classifier: Programming Language :: Python :: 3
Classifier: Operating System :: OS Independent
Requires-Python: >=3.6
License-File: LICENSE
Requires-Dist: numpy (==1.21.2)
Requires-Dist: matplotlib (==3.4.3)
Requires-Dist: validators (==0.18.2)
Requires-Dist: Pillow (==8.3.2)
Requires-Dist: protobuf (==3.18.1)
Requires-Dist: PyQt5 (==5.15.4)
